kv/sql/__init__.py
kv/sql/api.py
kv_sql-0.1.3.dist-info/METADATA
kv_sql-0.1.3.dist-info/WHEEL
kv_sql-0.1.3.dist-info/top_level.txt
kv_sql-0.1.3.dist-info/RECORD
