Metadata-Version: 2.1
Name: kv-sql
Version: 0.1.3
Summary: KV implementation over SQL Alchemy
Author-email: Marcel Claramunt <marcel@moveread.com>
Project-URL: repo, https://github.com/moveread/REPO.git
Requires-Python: >=3.10
